django_utility-0.2.2.dist-info/METADATA
django_utility-0.2.2.dist-info/RECORD
django_utility-0.2.2.dist-info/WHEEL
django_utility-0.2.2.dist-info/top_level.txt
tests/__init__.py
tests/test_settings.py
tests/tests.py
utility/__init__.py
utility/apps.py
utility/exceptions.py
utility/functions.py
utility/logger.py
utility/mixins.py
utility/tests.py
